uoapi/__init__.py
uoapi/config.yml
uoapi/metadata/metadata.json
uoapi/metadata/sensor_types.csv
uoapi/metadata/themes.csv
uoapi/metadata/variables.csv
uoapi/src/__init__.py
uoapi/src/api_client.py
uoapi/src/api_errors.py
uoapi/src/async_api_client.py
uoapi/test/test.py
uoapi/utils/__init__.py
uoapi/utils/data_getter.py
uoapi-0.2.6.dist-info/LICENSE
uoapi-0.2.6.dist-info/METADATA
uoapi-0.2.6.dist-info/WHEEL
uoapi-0.2.6.dist-info/RECORD
