Metadata-Version: 2.1
Name: uoapi
Version: 0.2.6
Summary: A robust Python client for interacting with the Newcastle Urban Observatory API (v1.1). This package provides a comprehensive interface for accessing and analyzing urban sensor data with built-in caching, configuration management, and data analysis capabilities.
License: MIT
Author: carrowmw
Author-email: c.morris-wiltshire@newcastle.ac.uk
Requires-Python: >=3.10,<4.0
Classifier: License :: OSI Approved :: MIT License
Classifier: Programming Language :: Python :: 3
Classifier: Programming Language :: Python :: 3.10
Classifier: Programming Language :: Python :: 3.11
Classifier: Programming Language :: Python :: 3.12
Requires-Dist: aiohttp (>=3.11.11,<4.0.0)
Requires-Dist: pandas (>=2.2.3,<3.0.0)
Requires-Dist: pyyaml (>=6.0.2,<7.0.0)
Requires-Dist: requests (>=2.32.3,<3.0.0)
